{"nodes": [{"id": "c_sgi_corban_sgi_backend_scripts_audit_schema_py", "label": "audit_schema.py", "file_type": "code", "source_file": "C:\\sgi-corban\\sgi-backend\\scripts\\audit_schema.py", "source_location": "L1"}, {"id": "scripts_audit_schema_get_sqlalchemy_models", "label": "get_sqlalchemy_models()", "file_type": "code", "source_file": "C:\\sgi-corban\\sgi-backend\\scripts\\audit_schema.py", "source_location": "L25"}, {"id": "scripts_audit_schema_get_database_schema", "label": "get_database_schema()", "file_type": "code", "source_file": "C:\\sgi-corban\\sgi-backend\\scripts\\audit_schema.py", "source_location": "L60"}, {"id": "scripts_audit_schema_compare_schemas", "label": "compare_schemas()", "file_type": "code", "source_file": "C:\\sgi-corban\\sgi-backend\\scripts\\audit_schema.py", "source_location": "L143"}, {"id": "scripts_audit_schema_main", "label": "main()", "file_type": "code", "source_file": "C:\\sgi-corban\\sgi-backend\\scripts\\audit_schema.py", "source_location": "L215"}, {"id": "scripts_audit_schema_rationale_1", "label": "Script de Auditor\u00eda: Modelos Python vs Base de Datos SQL Server.  Compara la e", "file_type": "rationale", "source_file": "C:\\sgi-corban\\sgi-backend\\scripts\\audit_schema.py", "source_location": "L1"}, {"id": "scripts_audit_schema_rationale_26", "label": "Lee todos los modelos registrados en SQLAlchemy Base.", "file_type": "rationale", "source_file": "C:\\sgi-corban\\sgi-backend\\scripts\\audit_schema.py", "source_location": "L26"}, {"id": "scripts_audit_schema_rationale_61", "label": "Lee la estructura real de las tablas en SQL Server.", "file_type": "rationale", "source_file": "C:\\sgi-corban\\sgi-backend\\scripts\\audit_schema.py", "source_location": "L61"}, {"id": "scripts_audit_schema_rationale_144", "label": "Compara modelos Python vs BD y retorna diferencias.", "file_type": "rationale", "source_file": "C:\\sgi-corban\\sgi-backend\\scripts\\audit_schema.py", "source_location": "L144"}], "edges": [{"source": "c_sgi_corban_sgi_backend_scripts_audit_schema_py", "target": "os", "relation": "imports", "context": "import", "confidence": "EXTRACTED", "source_file": "C:\\sgi-corban\\sgi-backend\\scripts\\audit_schema.py", "source_location": "L11", "weight": 1.0}, {"source": "c_sgi_corban_sgi_backend_scripts_audit_schema_py", "target": "sys", "relation": "imports", "context": "import", "confidence": "EXTRACTED", "source_file": "C:\\sgi-corban\\sgi-backend\\scripts\\audit_schema.py", "source_location": "L12", "weight": 1.0}, {"source": "c_sgi_corban_sgi_backend_scripts_audit_schema_py", "target": "pyodbc", "relation": "imports", "context": "import", "confidence": "EXTRACTED", "source_file": "C:\\sgi-corban\\sgi-backend\\scripts\\audit_schema.py", "source_location": "L13", "weight": 1.0}, {"source": "c_sgi_corban_sgi_backend_scripts_audit_schema_py", "target": "dotenv", "relation": "imports_from", "context": "import", "confidence": "EXTRACTED", "source_file": "C:\\sgi-corban\\sgi-backend\\scripts\\audit_schema.py", "source_location": "L14", "weight": 1.0}, {"source": "c_sgi_corban_sgi_backend_scripts_audit_schema_py", "target": "collections", "relation": "imports_from", "context": "import", "confidence": "EXTRACTED", "source_file": "C:\\sgi-corban\\sgi-backend\\scripts\\audit_schema.py", "source_location": "L15", "weight": 1.0}, {"source": "c_sgi_corban_sgi_backend_scripts_audit_schema_py", "target": "scripts_audit_schema_get_sqlalchemy_models", "relation": "contains", "confidence": "EXTRACTED", "source_file": "C:\\sgi-corban\\sgi-backend\\scripts\\audit_schema.py", "source_location": "L25", "weight": 1.0}, {"source": "c_sgi_corban_sgi_backend_scripts_audit_schema_py", "target": "scripts_audit_schema_get_database_schema", "relation": "contains", "confidence": "EXTRACTED", "source_file": "C:\\sgi-corban\\sgi-backend\\scripts\\audit_schema.py", "source_location": "L60", "weight": 1.0}, {"source": "c_sgi_corban_sgi_backend_scripts_audit_schema_py", "target": "scripts_audit_schema_compare_schemas", "relation": "contains", "confidence": "EXTRACTED", "source_file": "C:\\sgi-corban\\sgi-backend\\scripts\\audit_schema.py", "source_location": "L143", "weight": 1.0}, {"source": "c_sgi_corban_sgi_backend_scripts_audit_schema_py", "target": "scripts_audit_schema_main", "relation": "contains", "confidence": "EXTRACTED", "source_file": "C:\\sgi-corban\\sgi-backend\\scripts\\audit_schema.py", "source_location": "L215", "weight": 1.0}, {"source": "scripts_audit_schema_main", "target": "scripts_audit_schema_get_sqlalchemy_models", "relation": "calls", "context": "call", "confidence": "EXTRACTED", "source_file": "C:\\sgi-corban\\sgi-backend\\scripts\\audit_schema.py", "source_location": "L222", "weight": 1.0}, {"source": "scripts_audit_schema_main", "target": "scripts_audit_schema_get_database_schema", "relation": "calls", "context": "call", "confidence": "EXTRACTED", "source_file": "C:\\sgi-corban\\sgi-backend\\scripts\\audit_schema.py", "source_location": "L227", "weight": 1.0}, {"source": "scripts_audit_schema_main", "target": "scripts_audit_schema_compare_schemas", "relation": "calls", "context": "call", "confidence": "EXTRACTED", "source_file": "C:\\sgi-corban\\sgi-backend\\scripts\\audit_schema.py", "source_location": "L232", "weight": 1.0}, {"source": "scripts_audit_schema_rationale_1", "target": "c_sgi_corban_sgi_backend_scripts_audit_schema_py", "relation": "rationale_for", "confidence": "EXTRACTED", "source_file": "C:\\sgi-corban\\sgi-backend\\scripts\\audit_schema.py", "source_location": "L1", "weight": 1.0}, {"source": "scripts_audit_schema_rationale_26", "target": "scripts_audit_schema_get_sqlalchemy_models", "relation": "rationale_for", "confidence": "EXTRACTED", "source_file": "C:\\sgi-corban\\sgi-backend\\scripts\\audit_schema.py", "source_location": "L26", "weight": 1.0}, {"source": "scripts_audit_schema_rationale_61", "target": "scripts_audit_schema_get_database_schema", "relation": "rationale_for", "confidence": "EXTRACTED", "source_file": "C:\\sgi-corban\\sgi-backend\\scripts\\audit_schema.py", "source_location": "L61", "weight": 1.0}, {"source": "scripts_audit_schema_rationale_144", "target": "scripts_audit_schema_compare_schemas", "relation": "rationale_for", "confidence": "EXTRACTED", "source_file": "C:\\sgi-corban\\sgi-backend\\scripts\\audit_schema.py", "source_location": "L144", "weight": 1.0}], "raw_calls": [{"caller_nid": "scripts_audit_schema_get_sqlalchemy_models", "callee": "values", "is_member_call": true, "source_file": "C:\\sgi-corban\\sgi-backend\\scripts\\audit_schema.py", "source_location": "L32"}, {"caller_nid": "scripts_audit_schema_get_database_schema", "callee": "getenv", "is_member_call": true, "source_file": "C:\\sgi-corban\\sgi-backend\\scripts\\audit_schema.py", "source_location": "L62"}, {"caller_nid": "scripts_audit_schema_get_database_schema", "callee": "getenv", "is_member_call": true, "source_file": "C:\\sgi-corban\\sgi-backend\\scripts\\audit_schema.py", "source_location": "L63"}, {"caller_nid": "scripts_audit_schema_get_database_schema", "callee": "getenv", "is_member_call": true, "source_file": "C:\\sgi-corban\\sgi-backend\\scripts\\audit_schema.py", "source_location": "L64"}, {"caller_nid": "scripts_audit_schema_get_database_schema", "callee": "getenv", "is_member_call": true, "source_file": "C:\\sgi-corban\\sgi-backend\\scripts\\audit_schema.py", "source_location": "L65"}, {"caller_nid": "scripts_audit_schema_get_database_schema", "callee": "getenv", "is_member_call": true, "source_file": "C:\\sgi-corban\\sgi-backend\\scripts\\audit_schema.py", "source_location": "L66"}, {"caller_nid": "scripts_audit_schema_get_database_schema", "callee": "connect", "is_member_call": true, "source_file": "C:\\sgi-corban\\sgi-backend\\scripts\\audit_schema.py", "source_location": "L78"}, {"caller_nid": "scripts_audit_schema_get_database_schema", "callee": "cursor", "is_member_call": true, "source_file": "C:\\sgi-corban\\sgi-backend\\scripts\\audit_schema.py", "source_location": "L79"}, {"caller_nid": "scripts_audit_schema_get_database_schema", "callee": "execute", "is_member_call": true, "source_file": "C:\\sgi-corban\\sgi-backend\\scripts\\audit_schema.py", "source_location": "L82"}, {"caller_nid": "scripts_audit_schema_get_database_schema", "callee": "fetchall", "is_member_call": true, "source_file": "C:\\sgi-corban\\sgi-backend\\scripts\\audit_schema.py", "source_location": "L97"}, {"caller_nid": "scripts_audit_schema_get_database_schema", "callee": "execute", "is_member_call": true, "source_file": "C:\\sgi-corban\\sgi-backend\\scripts\\audit_schema.py", "source_location": "L116"}, {"caller_nid": "scripts_audit_schema_get_database_schema", "callee": "fetchall", "is_member_call": true, "source_file": "C:\\sgi-corban\\sgi-backend\\scripts\\audit_schema.py", "source_location": "L128"}, {"caller_nid": "scripts_audit_schema_get_database_schema", "callee": "close", "is_member_call": true, "source_file": "C:\\sgi-corban\\sgi-backend\\scripts\\audit_schema.py", "source_location": "L135"}, {"caller_nid": "scripts_audit_schema_compare_schemas", "callee": "keys", "is_member_call": true, "source_file": "C:\\sgi-corban\\sgi-backend\\scripts\\audit_schema.py", "source_location": "L151"}, {"caller_nid": "scripts_audit_schema_compare_schemas", "callee": "keys", "is_member_call": true, "source_file": "C:\\sgi-corban\\sgi-backend\\scripts\\audit_schema.py", "source_location": "L151"}, {"caller_nid": "scripts_audit_schema_compare_schemas", "callee": "append", "is_member_call": true, "source_file": "C:\\sgi-corban\\sgi-backend\\scripts\\audit_schema.py", "source_location": "L160"}, {"caller_nid": "scripts_audit_schema_compare_schemas", "callee": "join", "is_member_call": true, "source_file": "C:\\sgi-corban\\sgi-backend\\scripts\\audit_schema.py", "source_location": "L165"}, {"caller_nid": "scripts_audit_schema_compare_schemas", "callee": "keys", "is_member_call": true, "source_file": "C:\\sgi-corban\\sgi-backend\\scripts\\audit_schema.py", "source_location": "L165"}, {"caller_nid": "scripts_audit_schema_compare_schemas", "callee": "append", "is_member_call": true, "source_file": "C:\\sgi-corban\\sgi-backend\\scripts\\audit_schema.py", "source_location": "L166"}, {"caller_nid": "scripts_audit_schema_compare_schemas", "callee": "append", "is_member_call": true, "source_file": "C:\\sgi-corban\\sgi-backend\\scripts\\audit_schema.py", "source_location": "L167"}, {"caller_nid": "scripts_audit_schema_compare_schemas", "callee": "keys", "is_member_call": true, "source_file": "C:\\sgi-corban\\sgi-backend\\scripts\\audit_schema.py", "source_location": "L176"}, {"caller_nid": "scripts_audit_schema_compare_schemas", "callee": "append", "is_member_call": true, "source_file": "C:\\sgi-corban\\sgi-backend\\scripts\\audit_schema.py", "source_location": "L180"}, {"caller_nid": "scripts_audit_schema_compare_schemas", "callee": "keys", "is_member_call": true, "source_file": "C:\\sgi-corban\\sgi-backend\\scripts\\audit_schema.py", "source_location": "L184"}, {"caller_nid": "scripts_audit_schema_compare_schemas", "callee": "append", "is_member_call": true, "source_file": "C:\\sgi-corban\\sgi-backend\\scripts\\audit_schema.py", "source_location": "L187"}, {"caller_nid": "scripts_audit_schema_compare_schemas", "callee": "keys", "is_member_call": true, "source_file": "C:\\sgi-corban\\sgi-backend\\scripts\\audit_schema.py", "source_location": "L191"}, {"caller_nid": "scripts_audit_schema_compare_schemas", "callee": "get", "is_member_call": true, "source_file": "C:\\sgi-corban\\sgi-backend\\scripts\\audit_schema.py", "source_location": "L194"}, {"caller_nid": "scripts_audit_schema_compare_schemas", "callee": "append", "is_member_call": true, "source_file": "C:\\sgi-corban\\sgi-backend\\scripts\\audit_schema.py", "source_location": "L197"}, {"caller_nid": "scripts_audit_schema_compare_schemas", "callee": "append", "is_member_call": true, "source_file": "C:\\sgi-corban\\sgi-backend\\scripts\\audit_schema.py", "source_location": "L201"}, {"caller_nid": "scripts_audit_schema_compare_schemas", "callee": "extend", "is_member_call": true, "source_file": "C:\\sgi-corban\\sgi-backend\\scripts\\audit_schema.py", "source_location": "L202"}]}