{"nodes": [{"id": "c_sgi_corban_sgi_backend_app_services_comercial_media_service_py", "label": "media_service.py", "file_type": "code", "source_file": "C:\\sgi-corban\\sgi-backend\\app\\services\\comercial\\media_service.py", "source_location": "L1"}, {"id": "comercial_media_service_mediaservice", "label": "MediaService", "file_type": "code", "source_file": "C:\\sgi-corban\\sgi-backend\\app\\services\\comercial\\media_service.py", "source_location": "L41"}, {"id": "comercial_media_service_mediaservice_descargar_media", "label": ".descargar_media()", "file_type": "code", "source_file": "C:\\sgi-corban\\sgi-backend\\app\\services\\comercial\\media_service.py", "source_location": "L45"}, {"id": "str", "label": "str", "file_type": "code", "source_file": "C:\\sgi-corban\\sgi-backend\\app\\services\\comercial\\media_service.py", "source_location": "L45"}, {"id": "comercial_media_service_rationale_1", "label": "Servicio para descargar y almacenar archivos multimedia de WhatsApp.  Flujo: m", "file_type": "rationale", "source_file": "C:\\sgi-corban\\sgi-backend\\app\\services\\comercial\\media_service.py", "source_location": "L1"}, {"id": "comercial_media_service_rationale_42", "label": "Servicio para descargar medios de la API de WhatsApp Cloud.", "file_type": "rationale", "source_file": "C:\\sgi-corban\\sgi-backend\\app\\services\\comercial\\media_service.py", "source_location": "L42"}, {"id": "comercial_media_service_rationale_46", "label": "Descarga un archivo multimedia de WhatsApp y lo guarda localmente.", "file_type": "rationale", "source_file": "C:\\sgi-corban\\sgi-backend\\app\\services\\comercial\\media_service.py", "source_location": "L46"}], "edges": [{"source": "c_sgi_corban_sgi_backend_app_services_comercial_media_service_py", "target": "logging", "relation": "imports", "context": "import", "confidence": "EXTRACTED", "source_file": "C:\\sgi-corban\\sgi-backend\\app\\services\\comercial\\media_service.py", "source_location": "L5", "weight": 1.0}, {"source": "c_sgi_corban_sgi_backend_app_services_comercial_media_service_py", "target": "os", "relation": "imports", "context": "import", "confidence": "EXTRACTED", "source_file": "C:\\sgi-corban\\sgi-backend\\app\\services\\comercial\\media_service.py", "source_location": "L6", "weight": 1.0}, {"source": "c_sgi_corban_sgi_backend_app_services_comercial_media_service_py", "target": "uuid", "relation": "imports", "context": "import", "confidence": "EXTRACTED", "source_file": "C:\\sgi-corban\\sgi-backend\\app\\services\\comercial\\media_service.py", "source_location": "L7", "weight": 1.0}, {"source": "c_sgi_corban_sgi_backend_app_services_comercial_media_service_py", "target": "datetime", "relation": "imports_from", "context": "import", "confidence": "EXTRACTED", "source_file": "C:\\sgi-corban\\sgi-backend\\app\\services\\comercial\\media_service.py", "source_location": "L8", "weight": 1.0}, {"source": "c_sgi_corban_sgi_backend_app_services_comercial_media_service_py", "target": "httpx", "relation": "imports", "context": "import", "confidence": "EXTRACTED", "source_file": "C:\\sgi-corban\\sgi-backend\\app\\services\\comercial\\media_service.py", "source_location": "L10", "weight": 1.0}, {"source": "c_sgi_corban_sgi_backend_app_services_comercial_media_service_py", "target": "dotenv", "relation": "imports_from", "context": "import", "confidence": "EXTRACTED", "source_file": "C:\\sgi-corban\\sgi-backend\\app\\services\\comercial\\media_service.py", "source_location": "L11", "weight": 1.0}, {"source": "c_sgi_corban_sgi_backend_app_services_comercial_media_service_py", "target": "comercial_media_service_mediaservice", "relation": "contains", "confidence": "EXTRACTED", "source_file": "C:\\sgi-corban\\sgi-backend\\app\\services\\comercial\\media_service.py", "source_location": "L41", "weight": 1.0}, {"source": "comercial_media_service_mediaservice", "target": "comercial_media_service_mediaservice_descargar_media", "relation": "method", "confidence": "EXTRACTED", "source_file": "C:\\sgi-corban\\sgi-backend\\app\\services\\comercial\\media_service.py", "source_location": "L45", "weight": 1.0}, {"source": "comercial_media_service_mediaservice_descargar_media", "target": "str", "relation": "references", "context": "parameter_type", "confidence": "EXTRACTED", "source_file": "C:\\sgi-corban\\sgi-backend\\app\\services\\comercial\\media_service.py", "source_location": "L45", "weight": 1.0}, {"source": "comercial_media_service_mediaservice_descargar_media", "target": "str", "relation": "references", "context": "parameter_type", "confidence": "EXTRACTED", "source_file": "C:\\sgi-corban\\sgi-backend\\app\\services\\comercial\\media_service.py", "source_location": "L45", "weight": 1.0}, {"source": "comercial_media_service_rationale_1", "target": "c_sgi_corban_sgi_backend_app_services_comercial_media_service_py", "relation": "rationale_for", "confidence": "EXTRACTED", "source_file": "C:\\sgi-corban\\sgi-backend\\app\\services\\comercial\\media_service.py", "source_location": "L1", "weight": 1.0}, {"source": "comercial_media_service_rationale_42", "target": "comercial_media_service_mediaservice", "relation": "rationale_for", "confidence": "EXTRACTED", "source_file": "C:\\sgi-corban\\sgi-backend\\app\\services\\comercial\\media_service.py", "source_location": "L42", "weight": 1.0}, {"source": "comercial_media_service_rationale_46", "target": "comercial_media_service_mediaservice_descargar_media", "relation": "rationale_for", "confidence": "EXTRACTED", "source_file": "C:\\sgi-corban\\sgi-backend\\app\\services\\comercial\\media_service.py", "source_location": "L46", "weight": 1.0}], "raw_calls": [{"caller_nid": "comercial_media_service_mediaservice_descargar_media", "callee": "error", "is_member_call": true, "source_file": "C:\\sgi-corban\\sgi-backend\\app\\services\\comercial\\media_service.py", "source_location": "L57"}, {"caller_nid": "comercial_media_service_mediaservice_descargar_media", "callee": "AsyncClient", "is_member_call": true, "source_file": "C:\\sgi-corban\\sgi-backend\\app\\services\\comercial\\media_service.py", "source_location": "L65"}, {"caller_nid": "comercial_media_service_mediaservice_descargar_media", "callee": "get", "is_member_call": true, "source_file": "C:\\sgi-corban\\sgi-backend\\app\\services\\comercial\\media_service.py", "source_location": "L67"}, {"caller_nid": "comercial_media_service_mediaservice_descargar_media", "callee": "raise_for_status", "is_member_call": true, "source_file": "C:\\sgi-corban\\sgi-backend\\app\\services\\comercial\\media_service.py", "source_location": "L71"}, {"caller_nid": "comercial_media_service_mediaservice_descargar_media", "callee": "json", "is_member_call": true, "source_file": "C:\\sgi-corban\\sgi-backend\\app\\services\\comercial\\media_service.py", "source_location": "L72"}, {"caller_nid": "comercial_media_service_mediaservice_descargar_media", "callee": "get", "is_member_call": true, "source_file": "C:\\sgi-corban\\sgi-backend\\app\\services\\comercial\\media_service.py", "source_location": "L74"}, {"caller_nid": "comercial_media_service_mediaservice_descargar_media", "callee": "get", "is_member_call": true, "source_file": "C:\\sgi-corban\\sgi-backend\\app\\services\\comercial\\media_service.py", "source_location": "L75"}, {"caller_nid": "comercial_media_service_mediaservice_descargar_media", "callee": "error", "is_member_call": true, "source_file": "C:\\sgi-corban\\sgi-backend\\app\\services\\comercial\\media_service.py", "source_location": "L78"}, {"caller_nid": "comercial_media_service_mediaservice_descargar_media", "callee": "get", "is_member_call": true, "source_file": "C:\\sgi-corban\\sgi-backend\\app\\services\\comercial\\media_service.py", "source_location": "L82"}, {"caller_nid": "comercial_media_service_mediaservice_descargar_media", "callee": "raise_for_status", "is_member_call": true, "source_file": "C:\\sgi-corban\\sgi-backend\\app\\services\\comercial\\media_service.py", "source_location": "L86"}, {"caller_nid": "comercial_media_service_mediaservice_descargar_media", "callee": "get", "is_member_call": true, "source_file": "C:\\sgi-corban\\sgi-backend\\app\\services\\comercial\\media_service.py", "source_location": "L89"}, {"caller_nid": "comercial_media_service_mediaservice_descargar_media", "callee": "strftime", "is_member_call": true, "source_file": "C:\\sgi-corban\\sgi-backend\\app\\services\\comercial\\media_service.py", "source_location": "L90"}, {"caller_nid": "comercial_media_service_mediaservice_descargar_media", "callee": "now", "is_member_call": true, "source_file": "C:\\sgi-corban\\sgi-backend\\app\\services\\comercial\\media_service.py", "source_location": "L90"}, {"caller_nid": "comercial_media_service_mediaservice_descargar_media", "callee": "uuid4", "is_member_call": true, "source_file": "C:\\sgi-corban\\sgi-backend\\app\\services\\comercial\\media_service.py", "source_location": "L91"}, {"caller_nid": "comercial_media_service_mediaservice_descargar_media", "callee": "join", "is_member_call": true, "source_file": "C:\\sgi-corban\\sgi-backend\\app\\services\\comercial\\media_service.py", "source_location": "L94"}, {"caller_nid": "comercial_media_service_mediaservice_descargar_media", "callee": "makedirs", "is_member_call": true, "source_file": "C:\\sgi-corban\\sgi-backend\\app\\services\\comercial\\media_service.py", "source_location": "L95"}, {"caller_nid": "comercial_media_service_mediaservice_descargar_media", "callee": "join", "is_member_call": true, "source_file": "C:\\sgi-corban\\sgi-backend\\app\\services\\comercial\\media_service.py", "source_location": "L98"}, {"caller_nid": "comercial_media_service_mediaservice_descargar_media", "callee": "write", "is_member_call": true, "source_file": "C:\\sgi-corban\\sgi-backend\\app\\services\\comercial\\media_service.py", "source_location": "L100"}, {"caller_nid": "comercial_media_service_mediaservice_descargar_media", "callee": "info", "is_member_call": true, "source_file": "C:\\sgi-corban\\sgi-backend\\app\\services\\comercial\\media_service.py", "source_location": "L105"}, {"caller_nid": "comercial_media_service_mediaservice_descargar_media", "callee": "error", "is_member_call": true, "source_file": "C:\\sgi-corban\\sgi-backend\\app\\services\\comercial\\media_service.py", "source_location": "L117"}, {"caller_nid": "comercial_media_service_mediaservice_descargar_media", "callee": "error", "is_member_call": true, "source_file": "C:\\sgi-corban\\sgi-backend\\app\\services\\comercial\\media_service.py", "source_location": "L123"}]}