{"nodes": [{"id": "c_sgi_corban_sgi_backend_app_api_v1_comercial_contactos_py", "label": "contactos.py", "file_type": "code", "source_file": "C:\\sgi-corban\\sgi-backend\\app\\api\\v1\\comercial\\contactos.py", "source_location": "L1"}, {"id": "comercial_contactos_get_contactos", "label": "get_contactos()", "file_type": "code", "source_file": "C:\\sgi-corban\\sgi-backend\\app\\api\\v1\\comercial\\contactos.py", "source_location": "L20"}, {"id": "str", "label": "str", "file_type": "code", "source_file": "C:\\sgi-corban\\sgi-backend\\app\\api\\v1\\comercial\\contactos.py", "source_location": "L20"}, {"id": "asyncsession", "label": "AsyncSession", "file_type": "code", "source_file": "C:\\sgi-corban\\sgi-backend\\app\\api\\v1\\comercial\\contactos.py", "source_location": "L20"}, {"id": "comercial_contactos_create_contacto", "label": "create_contacto()", "file_type": "code", "source_file": "C:\\sgi-corban\\sgi-backend\\app\\api\\v1\\comercial\\contactos.py", "source_location": "L31"}, {"id": "contactocreate", "label": "ContactoCreate", "file_type": "code", "source_file": "C:\\sgi-corban\\sgi-backend\\app\\api\\v1\\comercial\\contactos.py", "source_location": "L31"}, {"id": "comercial_contactos_set_contacto_principal", "label": "set_contacto_principal()", "file_type": "code", "source_file": "C:\\sgi-corban\\sgi-backend\\app\\api\\v1\\comercial\\contactos.py", "source_location": "L42"}, {"id": "int", "label": "int", "file_type": "code", "source_file": "C:\\sgi-corban\\sgi-backend\\app\\api\\v1\\comercial\\contactos.py", "source_location": "L42"}, {"id": "bool", "label": "bool", "file_type": "code", "source_file": "C:\\sgi-corban\\sgi-backend\\app\\api\\v1\\comercial\\contactos.py", "source_location": "L42"}, {"id": "comercial_contactos_update_contacto", "label": "update_contacto()", "file_type": "code", "source_file": "C:\\sgi-corban\\sgi-backend\\app\\api\\v1\\comercial\\contactos.py", "source_location": "L55"}, {"id": "contactoupdate", "label": "ContactoUpdate", "file_type": "code", "source_file": "C:\\sgi-corban\\sgi-backend\\app\\api\\v1\\comercial\\contactos.py", "source_location": "L55"}, {"id": "comercial_contactos_delete_contacto", "label": "delete_contacto()", "file_type": "code", "source_file": "C:\\sgi-corban\\sgi-backend\\app\\api\\v1\\comercial\\contactos.py", "source_location": "L67"}, {"id": "comercial_contactos_get_contactos_paginados", "label": "get_contactos_paginados()", "file_type": "code", "source_file": "C:\\sgi-corban\\sgi-backend\\app\\api\\v1\\comercial\\contactos.py", "source_location": "L78"}, {"id": "comercial_contactos_get_estadisticas", "label": "get_estadisticas()", "file_type": "code", "source_file": "C:\\sgi-corban\\sgi-backend\\app\\api\\v1\\comercial\\contactos.py", "source_location": "L92"}, {"id": "comercial_contactos_get_kpis_gestion", "label": "get_kpis_gestion()", "file_type": "code", "source_file": "C:\\sgi-corban\\sgi-backend\\app\\api\\v1\\comercial\\contactos.py", "source_location": "L102"}, {"id": "comercial_contactos_assign_leads_batch", "label": "assign_leads_batch()", "file_type": "code", "source_file": "C:\\sgi-corban\\sgi-backend\\app\\api\\v1\\comercial\\contactos.py", "source_location": "L114"}, {"id": "comercial_contactos_get_mis_contactos_asignados", "label": "get_mis_contactos_asignados()", "file_type": "code", "source_file": "C:\\sgi-corban\\sgi-backend\\app\\api\\v1\\comercial\\contactos.py", "source_location": "L128"}, {"id": "comercial_contactos_cargar_base", "label": "cargar_base()", "file_type": "code", "source_file": "C:\\sgi-corban\\sgi-backend\\app\\api\\v1\\comercial\\contactos.py", "source_location": "L138"}, {"id": "comercial_contactos_create_contacto_manual", "label": "create_contacto_manual()", "file_type": "code", "source_file": "C:\\sgi-corban\\sgi-backend\\app\\api\\v1\\comercial\\contactos.py", "source_location": "L150"}, {"id": "contactomanualcreate", "label": "ContactoManualCreate", "file_type": "code", "source_file": "C:\\sgi-corban\\sgi-backend\\app\\api\\v1\\comercial\\contactos.py", "source_location": "L150"}, {"id": "comercial_contactos_asignar_lead_manualmente", "label": "asignar_lead_manualmente()", "file_type": "code", "source_file": "C:\\sgi-corban\\sgi-backend\\app\\api\\v1\\comercial\\contactos.py", "source_location": "L161"}, {"id": "asignarleadmanual", "label": "AsignarLeadManual", "file_type": "code", "source_file": "C:\\sgi-corban\\sgi-backend\\app\\api\\v1\\comercial\\contactos.py", "source_location": "L161"}, {"id": "comercial_contactos_actualizar_feedback", "label": "actualizar_feedback()", "file_type": "code", "source_file": "C:\\sgi-corban\\sgi-backend\\app\\api\\v1\\comercial\\contactos.py", "source_location": "L173"}, {"id": "comercial_contactos_enviar_feedback_lote", "label": "enviar_feedback_lote()", "file_type": "code", "source_file": "C:\\sgi-corban\\sgi-backend\\app\\api\\v1\\comercial\\contactos.py", "source_location": "L186"}, {"id": "comercial_contactos_get_filtros_base", "label": "get_filtros_base()", "file_type": "code", "source_file": "C:\\sgi-corban\\sgi-backend\\app\\api\\v1\\comercial\\contactos.py", "source_location": "L196"}, {"id": "comercial_contactos_rationale_25", "label": "Obtiene contactos por RUC.", "file_type": "rationale", "source_file": "C:\\sgi-corban\\sgi-backend\\app\\api\\v1\\comercial\\contactos.py", "source_location": "L25"}, {"id": "comercial_contactos_rationale_36", "label": "Crea un nuevo contacto.", "file_type": "rationale", "source_file": "C:\\sgi-corban\\sgi-backend\\app\\api\\v1\\comercial\\contactos.py", "source_location": "L36"}, {"id": "comercial_contactos_rationale_49", "label": "Establece o quita un contacto como principal para un RUC espec\u00edfico.", "file_type": "rationale", "source_file": "C:\\sgi-corban\\sgi-backend\\app\\api\\v1\\comercial\\contactos.py", "source_location": "L49"}, {"id": "comercial_contactos_rationale_61", "label": "Actualiza un contacto existente.", "file_type": "rationale", "source_file": "C:\\sgi-corban\\sgi-backend\\app\\api\\v1\\comercial\\contactos.py", "source_location": "L61"}, {"id": "comercial_contactos_rationale_72", "label": "Desactiva un contacto (soft delete).", "file_type": "rationale", "source_file": "C:\\sgi-corban\\sgi-backend\\app\\api\\v1\\comercial\\contactos.py", "source_location": "L72"}, {"id": "comercial_contactos_rationale_86", "label": "Lista contactos paginados con razon_social, caso, estado y estad\u00edsticas de dispo", "file_type": "rationale", "source_file": "C:\\sgi-corban\\sgi-backend\\app\\api\\v1\\comercial\\contactos.py", "source_location": "L86"}, {"id": "comercial_contactos_rationale_96", "label": "Retorna estad\u00edsticas de contactos: total, disponibles, asignados, en_gestion.", "file_type": "rationale", "source_file": "C:\\sgi-corban\\sgi-backend\\app\\api\\v1\\comercial\\contactos.py", "source_location": "L96"}, {"id": "comercial_contactos_rationale_108", "label": "Retorna KPIs de gesti\u00f3n para dashboard (Total Repartido, Contactabilidad, Positi", "file_type": "rationale", "source_file": "C:\\sgi-corban\\sgi-backend\\app\\api\\v1\\comercial\\contactos.py", "source_location": "L108"}, {"id": "comercial_contactos_rationale_118", "label": "Asigna un lote de contactos al comercial actual.", "file_type": "rationale", "source_file": "C:\\sgi-corban\\sgi-backend\\app\\api\\v1\\comercial\\contactos.py", "source_location": "L118"}, {"id": "comercial_contactos_rationale_132", "label": "Obtiene los contactos asignados al comercial actual.", "file_type": "rationale", "source_file": "C:\\sgi-corban\\sgi-backend\\app\\api\\v1\\comercial\\contactos.py", "source_location": "L132"}, {"id": "comercial_contactos_rationale_144", "label": "Carga 50 contactos de empresas \u00fanicas para el comercial.", "file_type": "rationale", "source_file": "C:\\sgi-corban\\sgi-backend\\app\\api\\v1\\comercial\\contactos.py", "source_location": "L144"}, {"id": "comercial_contactos_rationale_155", "label": "Crea un contacto manual asociado a un RUC y lo asigna al comercial.", "file_type": "rationale", "source_file": "C:\\sgi-corban\\sgi-backend\\app\\api\\v1\\comercial\\contactos.py", "source_location": "L155"}, {"id": "comercial_contactos_rationale_167", "label": "Deriva manualmente un lead (RUC) a un comercial espec\u00edfico. Uso para Jefaturas.", "file_type": "rationale", "source_file": "C:\\sgi-corban\\sgi-backend\\app\\api\\v1\\comercial\\contactos.py", "source_location": "L167"}, {"id": "comercial_contactos_rationale_180", "label": "Actualiza el feedback de un contacto (caso y comentario).", "file_type": "rationale", "source_file": "C:\\sgi-corban\\sgi-backend\\app\\api\\v1\\comercial\\contactos.py", "source_location": "L180"}, {"id": "comercial_contactos_rationale_190", "label": "Env\u00eda el feedback de todos los contactos asignados y los marca como gestionados.", "file_type": "rationale", "source_file": "C:\\sgi-corban\\sgi-backend\\app\\api\\v1\\comercial\\contactos.py", "source_location": "L190"}, {"id": "comercial_contactos_rationale_200", "label": "Obtiene los pa\u00edses y partidas arancelarias disponibles para filtrar.", "file_type": "rationale", "source_file": "C:\\sgi-corban\\sgi-backend\\app\\api\\v1\\comercial\\contactos.py", "source_location": "L200"}], "edges": [{"source": "c_sgi_corban_sgi_backend_app_api_v1_comercial_contactos_py", "target": "fastapi", "relation": "imports_from", "context": "import", "confidence": "EXTRACTED", "source_file": "C:\\sgi-corban\\sgi-backend\\app\\api\\v1\\comercial\\contactos.py", "source_location": "L1", "weight": 1.0}, {"source": "c_sgi_corban_sgi_backend_app_api_v1_comercial_contactos_py", "target": "sqlalchemy_ext_asyncio", "relation": "imports_from", "context": "import", "confidence": "EXTRACTED", "source_file": "C:\\sgi-corban\\sgi-backend\\app\\api\\v1\\comercial\\contactos.py", "source_location": "L2", "weight": 1.0}, {"source": "c_sgi_corban_sgi_backend_app_api_v1_comercial_contactos_py", "target": "typing", "relation": "imports_from", "context": "import", "confidence": "EXTRACTED", "source_file": "C:\\sgi-corban\\sgi-backend\\app\\api\\v1\\comercial\\contactos.py", "source_location": "L3", "weight": 1.0}, {"source": "c_sgi_corban_sgi_backend_app_api_v1_comercial_contactos_py", "target": "app_database_db_connection", "relation": "imports_from", "context": "import", "confidence": "EXTRACTED", "source_file": "C:\\sgi-corban\\sgi-backend\\app\\api\\v1\\comercial\\contactos.py", "source_location": "L4", "weight": 1.0}, {"source": "c_sgi_corban_sgi_backend_app_api_v1_comercial_contactos_py", "target": "app_core_security", "relation": "imports_from", "context": "import", "confidence": "EXTRACTED", "source_file": "C:\\sgi-corban\\sgi-backend\\app\\api\\v1\\comercial\\contactos.py", "source_location": "L5", "weight": 1.0}, {"source": "c_sgi_corban_sgi_backend_app_api_v1_comercial_contactos_py", "target": "app_core_dependencies", "relation": "imports_from", "context": "import", "confidence": "EXTRACTED", "source_file": "C:\\sgi-corban\\sgi-backend\\app\\api\\v1\\comercial\\contactos.py", "source_location": "L6", "weight": 1.0}, {"source": "c_sgi_corban_sgi_backend_app_api_v1_comercial_contactos_py", "target": "app_services_contactos_service", "relation": "imports_from", "context": "import", "confidence": "EXTRACTED", "source_file": "C:\\sgi-corban\\sgi-backend\\app\\api\\v1\\comercial\\contactos.py", "source_location": "L7", "weight": 1.0}, {"source": "c_sgi_corban_sgi_backend_app_api_v1_comercial_contactos_py", "target": "app_schemas_comercial_contactos", "relation": "imports_from", "context": "import", "confidence": "EXTRACTED", "source_file": "C:\\sgi-corban\\sgi-backend\\app\\api\\v1\\comercial\\contactos.py", "source_location": "L8", "weight": 1.0}, {"source": "c_sgi_corban_sgi_backend_app_api_v1_comercial_contactos_py", "target": "comercial_contactos_get_contactos", "relation": "contains", "confidence": "EXTRACTED", "source_file": "C:\\sgi-corban\\sgi-backend\\app\\api\\v1\\comercial\\contactos.py", "source_location": "L20", "weight": 1.0}, {"source": "comercial_contactos_get_contactos", "target": "str", "relation": "references", "context": "parameter_type", "confidence": "EXTRACTED", "source_file": "C:\\sgi-corban\\sgi-backend\\app\\api\\v1\\comercial\\contactos.py", "source_location": "L20", "weight": 1.0}, {"source": "comercial_contactos_get_contactos", "target": "asyncsession", "relation": "references", "context": "parameter_type", "confidence": "EXTRACTED", "source_file": "C:\\sgi-corban\\sgi-backend\\app\\api\\v1\\comercial\\contactos.py", "source_location": "L20", "weight": 1.0}, {"source": "c_sgi_corban_sgi_backend_app_api_v1_comercial_contactos_py", "target": "comercial_contactos_create_contacto", "relation": "contains", "confidence": "EXTRACTED", "source_file": "C:\\sgi-corban\\sgi-backend\\app\\api\\v1\\comercial\\contactos.py", "source_location": "L31", "weight": 1.0}, {"source": "comercial_contactos_create_contacto", "target": "contactocreate", "relation": "references", "context": "parameter_type", "confidence": "EXTRACTED", "source_file": "C:\\sgi-corban\\sgi-backend\\app\\api\\v1\\comercial\\contactos.py", "source_location": "L31", "weight": 1.0}, {"source": "comercial_contactos_create_contacto", "target": "asyncsession", "relation": "references", "context": "parameter_type", "confidence": "EXTRACTED", "source_file": "C:\\sgi-corban\\sgi-backend\\app\\api\\v1\\comercial\\contactos.py", "source_location": "L31", "weight": 1.0}, {"source": "c_sgi_corban_sgi_backend_app_api_v1_comercial_contactos_py", "target": "comercial_contactos_set_contacto_principal", "relation": "contains", "confidence": "EXTRACTED", "source_file": "C:\\sgi-corban\\sgi-backend\\app\\api\\v1\\comercial\\contactos.py", "source_location": "L42", "weight": 1.0}, {"source": "comercial_contactos_set_contacto_principal", "target": "str", "relation": "references", "context": "parameter_type", "confidence": "EXTRACTED", "source_file": "C:\\sgi-corban\\sgi-backend\\app\\api\\v1\\comercial\\contactos.py", "source_location": "L42", "weight": 1.0}, {"source": "comercial_contactos_set_contacto_principal", "target": "int", "relation": "references", "context": "parameter_type", "confidence": "EXTRACTED", "source_file": "C:\\sgi-corban\\sgi-backend\\app\\api\\v1\\comercial\\contactos.py", "source_location": "L42", "weight": 1.0}, {"source": "comercial_contactos_set_contacto_principal", "target": "bool", "relation": "references", "context": "parameter_type", "confidence": "EXTRACTED", "source_file": "C:\\sgi-corban\\sgi-backend\\app\\api\\v1\\comercial\\contactos.py", "source_location": "L42", "weight": 1.0}, {"source": "comercial_contactos_set_contacto_principal", "target": "asyncsession", "relation": "references", "context": "parameter_type", "confidence": "EXTRACTED", "source_file": "C:\\sgi-corban\\sgi-backend\\app\\api\\v1\\comercial\\contactos.py", "source_location": "L42", "weight": 1.0}, {"source": "c_sgi_corban_sgi_backend_app_api_v1_comercial_contactos_py", "target": "comercial_contactos_update_contacto", "relation": "contains", "confidence": "EXTRACTED", "source_file": "C:\\sgi-corban\\sgi-backend\\app\\api\\v1\\comercial\\contactos.py", "source_location": "L55", "weight": 1.0}, {"source": "comercial_contactos_update_contacto", "target": "int", "relation": "references", "context": "parameter_type", "confidence": "EXTRACTED", "source_file": "C:\\sgi-corban\\sgi-backend\\app\\api\\v1\\comercial\\contactos.py", "source_location": "L55", "weight": 1.0}, {"source": "comercial_contactos_update_contacto", "target": "contactoupdate", "relation": "references", "context": "parameter_type", "confidence": "EXTRACTED", "source_file": "C:\\sgi-corban\\sgi-backend\\app\\api\\v1\\comercial\\contactos.py", "source_location": "L55", "weight": 1.0}, {"source": "comercial_contactos_update_contacto", "target": "asyncsession", "relation": "references", "context": "parameter_type", "confidence": "EXTRACTED", "source_file": "C:\\sgi-corban\\sgi-backend\\app\\api\\v1\\comercial\\contactos.py", "source_location": "L55", "weight": 1.0}, {"source": "c_sgi_corban_sgi_backend_app_api_v1_comercial_contactos_py", "target": "comercial_contactos_delete_contacto", "relation": "contains", "confidence": "EXTRACTED", "source_file": "C:\\sgi-corban\\sgi-backend\\app\\api\\v1\\comercial\\contactos.py", "source_location": "L67", "weight": 1.0}, {"source": "comercial_contactos_delete_contacto", "target": "int", "relation": "references", "context": "parameter_type", "confidence": "EXTRACTED", "source_file": "C:\\sgi-corban\\sgi-backend\\app\\api\\v1\\comercial\\contactos.py", "source_location": "L67", "weight": 1.0}, {"source": "comercial_contactos_delete_contacto", "target": "asyncsession", "relation": "references", "context": "parameter_type", "confidence": "EXTRACTED", "source_file": "C:\\sgi-corban\\sgi-backend\\app\\api\\v1\\comercial\\contactos.py", "source_location": "L67", "weight": 1.0}, {"source": "c_sgi_corban_sgi_backend_app_api_v1_comercial_contactos_py", "target": "comercial_contactos_get_contactos_paginados", "relation": "contains", "confidence": "EXTRACTED", "source_file": "C:\\sgi-corban\\sgi-backend\\app\\api\\v1\\comercial\\contactos.py", "source_location": "L78", "weight": 1.0}, {"source": "comercial_contactos_get_contactos_paginados", "target": "int", "relation": "references", "context": "parameter_type", "confidence": "EXTRACTED", "source_file": "C:\\sgi-corban\\sgi-backend\\app\\api\\v1\\comercial\\contactos.py", "source_location": "L78", "weight": 1.0}, {"source": "comercial_contactos_get_contactos_paginados", "target": "int", "relation": "references", "context": "parameter_type", "confidence": "EXTRACTED", "source_file": "C:\\sgi-corban\\sgi-backend\\app\\api\\v1\\comercial\\contactos.py", "source_location": "L78", "weight": 1.0}, {"source": "comercial_contactos_get_contactos_paginados", "target": "str", "relation": "references", "context": "parameter_type", "confidence": "EXTRACTED", "source_file": "C:\\sgi-corban\\sgi-backend\\app\\api\\v1\\comercial\\contactos.py", "source_location": "L78", "weight": 1.0}, {"source": "comercial_contactos_get_contactos_paginados", "target": "str", "relation": "references", "context": "parameter_type", "confidence": "EXTRACTED", "source_file": "C:\\sgi-corban\\sgi-backend\\app\\api\\v1\\comercial\\contactos.py", "source_location": "L78", "weight": 1.0}, {"source": "comercial_contactos_get_contactos_paginados", "target": "asyncsession", "relation": "references", "context": "parameter_type", "confidence": "EXTRACTED", "source_file": "C:\\sgi-corban\\sgi-backend\\app\\api\\v1\\comercial\\contactos.py", "source_location": "L78", "weight": 1.0}, {"source": "c_sgi_corban_sgi_backend_app_api_v1_comercial_contactos_py", "target": "comercial_contactos_get_estadisticas", "relation": "contains", "confidence": "EXTRACTED", "source_file": "C:\\sgi-corban\\sgi-backend\\app\\api\\v1\\comercial\\contactos.py", "source_location": "L92", "weight": 1.0}, {"source": "comercial_contactos_get_estadisticas", "target": "asyncsession", "relation": "references", "context": "parameter_type", "confidence": "EXTRACTED", "source_file": "C:\\sgi-corban\\sgi-backend\\app\\api\\v1\\comercial\\contactos.py", "source_location": "L92", "weight": 1.0}, {"source": "c_sgi_corban_sgi_backend_app_api_v1_comercial_contactos_py", "target": "comercial_contactos_get_kpis_gestion", "relation": "contains", "confidence": "EXTRACTED", "source_file": "C:\\sgi-corban\\sgi-backend\\app\\api\\v1\\comercial\\contactos.py", "source_location": "L102", "weight": 1.0}, {"source": "comercial_contactos_get_kpis_gestion", "target": "str", "relation": "references", "context": "parameter_type", "confidence": "EXTRACTED", "source_file": "C:\\sgi-corban\\sgi-backend\\app\\api\\v1\\comercial\\contactos.py", "source_location": "L102", "weight": 1.0}, {"source": "comercial_contactos_get_kpis_gestion", "target": "str", "relation": "references", "context": "parameter_type", "confidence": "EXTRACTED", "source_file": "C:\\sgi-corban\\sgi-backend\\app\\api\\v1\\comercial\\contactos.py", "source_location": "L102", "weight": 1.0}, {"source": "comercial_contactos_get_kpis_gestion", "target": "asyncsession", "relation": "references", "context": "parameter_type", "confidence": "EXTRACTED", "source_file": "C:\\sgi-corban\\sgi-backend\\app\\api\\v1\\comercial\\contactos.py", "source_location": "L102", "weight": 1.0}, {"source": "c_sgi_corban_sgi_backend_app_api_v1_comercial_contactos_py", "target": "comercial_contactos_assign_leads_batch", "relation": "contains", "confidence": "EXTRACTED", "source_file": "C:\\sgi-corban\\sgi-backend\\app\\api\\v1\\comercial\\contactos.py", "source_location": "L114", "weight": 1.0}, {"source": "comercial_contactos_assign_leads_batch", "target": "asyncsession", "relation": "references", "context": "parameter_type", "confidence": "EXTRACTED", "source_file": "C:\\sgi-corban\\sgi-backend\\app\\api\\v1\\comercial\\contactos.py", "source_location": "L114", "weight": 1.0}, {"source": "comercial_contactos_assign_leads_batch", "target": "int", "relation": "references", "context": "parameter_type", "confidence": "EXTRACTED", "source_file": "C:\\sgi-corban\\sgi-backend\\app\\api\\v1\\comercial\\contactos.py", "source_location": "L114", "weight": 1.0}, {"source": "c_sgi_corban_sgi_backend_app_api_v1_comercial_contactos_py", "target": "comercial_contactos_get_mis_contactos_asignados", "relation": "contains", "confidence": "EXTRACTED", "source_file": "C:\\sgi-corban\\sgi-backend\\app\\api\\v1\\comercial\\contactos.py", "source_location": "L128", "weight": 1.0}, {"source": "comercial_contactos_get_mis_contactos_asignados", "target": "asyncsession", "relation": "references", "context": "parameter_type", "confidence": "EXTRACTED", "source_file": "C:\\sgi-corban\\sgi-backend\\app\\api\\v1\\comercial\\contactos.py", "source_location": "L128", "weight": 1.0}, {"source": "comercial_contactos_get_mis_contactos_asignados", "target": "int", "relation": "references", "context": "parameter_type", "confidence": "EXTRACTED", "source_file": "C:\\sgi-corban\\sgi-backend\\app\\api\\v1\\comercial\\contactos.py", "source_location": "L128", "weight": 1.0}, {"source": "c_sgi_corban_sgi_backend_app_api_v1_comercial_contactos_py", "target": "comercial_contactos_cargar_base", "relation": "contains", "confidence": "EXTRACTED", "source_file": "C:\\sgi-corban\\sgi-backend\\app\\api\\v1\\comercial\\contactos.py", "source_location": "L138", "weight": 1.0}, {"source": "comercial_contactos_cargar_base", "target": "str", "relation": "references", "context": "generic_arg", "confidence": "EXTRACTED", "source_file": "C:\\sgi-corban\\sgi-backend\\app\\api\\v1\\comercial\\contactos.py", "source_location": "L138", "weight": 1.0}, {"source": "comercial_contactos_cargar_base", "target": "str", "relation": "references", "context": "generic_arg", "confidence": "EXTRACTED", "source_file": "C:\\sgi-corban\\sgi-backend\\app\\api\\v1\\comercial\\contactos.py", "source_location": "L138", "weight": 1.0}, {"source": "comercial_contactos_cargar_base", "target": "asyncsession", "relation": "references", "context": "parameter_type", "confidence": "EXTRACTED", "source_file": "C:\\sgi-corban\\sgi-backend\\app\\api\\v1\\comercial\\contactos.py", "source_location": "L138", "weight": 1.0}, {"source": "comercial_contactos_cargar_base", "target": "int", "relation": "references", "context": "parameter_type", "confidence": "EXTRACTED", "source_file": "C:\\sgi-corban\\sgi-backend\\app\\api\\v1\\comercial\\contactos.py", "source_location": "L138", "weight": 1.0}, {"source": "c_sgi_corban_sgi_backend_app_api_v1_comercial_contactos_py", "target": "comercial_contactos_create_contacto_manual", "relation": "contains", "confidence": "EXTRACTED", "source_file": "C:\\sgi-corban\\sgi-backend\\app\\api\\v1\\comercial\\contactos.py", "source_location": "L150", "weight": 1.0}, {"source": "comercial_contactos_create_contacto_manual", "target": "contactomanualcreate", "relation": "references", "context": "parameter_type", "confidence": "EXTRACTED", "source_file": "C:\\sgi-corban\\sgi-backend\\app\\api\\v1\\comercial\\contactos.py", "source_location": "L150", "weight": 1.0}, {"source": "comercial_contactos_create_contacto_manual", "target": "asyncsession", "relation": "references", "context": "parameter_type", "confidence": "EXTRACTED", "source_file": "C:\\sgi-corban\\sgi-backend\\app\\api\\v1\\comercial\\contactos.py", "source_location": "L150", "weight": 1.0}, {"source": "comercial_contactos_create_contacto_manual", "target": "int", "relation": "references", "context": "parameter_type", "confidence": "EXTRACTED", "source_file": "C:\\sgi-corban\\sgi-backend\\app\\api\\v1\\comercial\\contactos.py", "source_location": "L150", "weight": 1.0}, {"source": "c_sgi_corban_sgi_backend_app_api_v1_comercial_contactos_py", "target": "comercial_contactos_asignar_lead_manualmente", "relation": "contains", "confidence": "EXTRACTED", "source_file": "C:\\sgi-corban\\sgi-backend\\app\\api\\v1\\comercial\\contactos.py", "source_location": "L161", "weight": 1.0}, {"source": "comercial_contactos_asignar_lead_manualmente", "target": "str", "relation": "references", "context": "parameter_type", "confidence": "EXTRACTED", "source_file": "C:\\sgi-corban\\sgi-backend\\app\\api\\v1\\comercial\\contactos.py", "source_location": "L161", "weight": 1.0}, {"source": "comercial_contactos_asignar_lead_manualmente", "target": "asignarleadmanual", "relation": "references", "context": "parameter_type", "confidence": "EXTRACTED", "source_file": "C:\\sgi-corban\\sgi-backend\\app\\api\\v1\\comercial\\contactos.py", "source_location": "L161", "weight": 1.0}, {"source": "comercial_contactos_asignar_lead_manualmente", "target": "asyncsession", "relation": "references", "context": "parameter_type", "confidence": "EXTRACTED", "source_file": "C:\\sgi-corban\\sgi-backend\\app\\api\\v1\\comercial\\contactos.py", "source_location": "L161", "weight": 1.0}, {"source": "comercial_contactos_asignar_lead_manualmente", "target": "int", "relation": "references", "context": "parameter_type", "confidence": "EXTRACTED", "source_file": "C:\\sgi-corban\\sgi-backend\\app\\api\\v1\\comercial\\contactos.py", "source_location": "L161", "weight": 1.0}, {"source": "c_sgi_corban_sgi_backend_app_api_v1_comercial_contactos_py", "target": "comercial_contactos_actualizar_feedback", "relation": "contains", "confidence": "EXTRACTED", "source_file": "C:\\sgi-corban\\sgi-backend\\app\\api\\v1\\comercial\\contactos.py", "source_location": "L173", "weight": 1.0}, {"source": "comercial_contactos_actualizar_feedback", "target": "int", "relation": "references", "context": "parameter_type", "confidence": "EXTRACTED", "source_file": "C:\\sgi-corban\\sgi-backend\\app\\api\\v1\\comercial\\contactos.py", "source_location": "L173", "weight": 1.0}, {"source": "comercial_contactos_actualizar_feedback", "target": "int", "relation": "references", "context": "parameter_type", "confidence": "EXTRACTED", "source_file": "C:\\sgi-corban\\sgi-backend\\app\\api\\v1\\comercial\\contactos.py", "source_location": "L173", "weight": 1.0}, {"source": "comercial_contactos_actualizar_feedback", "target": "str", "relation": "references", "context": "parameter_type", "confidence": "EXTRACTED", "source_file": "C:\\sgi-corban\\sgi-backend\\app\\api\\v1\\comercial\\contactos.py", "source_location": "L173", "weight": 1.0}, {"source": "comercial_contactos_actualizar_feedback", "target": "asyncsession", "relation": "references", "context": "parameter_type", "confidence": "EXTRACTED", "source_file": "C:\\sgi-corban\\sgi-backend\\app\\api\\v1\\comercial\\contactos.py", "source_location": "L173", "weight": 1.0}, {"source": "comercial_contactos_actualizar_feedback", "target": "int", "relation": "references", "context": "parameter_type", "confidence": "EXTRACTED", "source_file": "C:\\sgi-corban\\sgi-backend\\app\\api\\v1\\comercial\\contactos.py", "source_location": "L173", "weight": 1.0}, {"source": "c_sgi_corban_sgi_backend_app_api_v1_comercial_contactos_py", "target": "comercial_contactos_enviar_feedback_lote", "relation": "contains", "confidence": "EXTRACTED", "source_file": "C:\\sgi-corban\\sgi-backend\\app\\api\\v1\\comercial\\contactos.py", "source_location": "L186", "weight": 1.0}, {"source": "comercial_contactos_enviar_feedback_lote", "target": "asyncsession", "relation": "references", "context": "parameter_type", "confidence": "EXTRACTED", "source_file": "C:\\sgi-corban\\sgi-backend\\app\\api\\v1\\comercial\\contactos.py", "source_location": "L186", "weight": 1.0}, {"source": "comercial_contactos_enviar_feedback_lote", "target": "int", "relation": "references", "context": "parameter_type", "confidence": "EXTRACTED", "source_file": "C:\\sgi-corban\\sgi-backend\\app\\api\\v1\\comercial\\contactos.py", "source_location": "L186", "weight": 1.0}, {"source": "c_sgi_corban_sgi_backend_app_api_v1_comercial_contactos_py", "target": "comercial_contactos_get_filtros_base", "relation": "contains", "confidence": "EXTRACTED", "source_file": "C:\\sgi-corban\\sgi-backend\\app\\api\\v1\\comercial\\contactos.py", "source_location": "L196", "weight": 1.0}, {"source": "comercial_contactos_get_filtros_base", "target": "asyncsession", "relation": "references", "context": "parameter_type", "confidence": "EXTRACTED", "source_file": "C:\\sgi-corban\\sgi-backend\\app\\api\\v1\\comercial\\contactos.py", "source_location": "L196", "weight": 1.0}, {"source": "comercial_contactos_rationale_25", "target": "comercial_contactos_get_contactos", "relation": "rationale_for", "confidence": "EXTRACTED", "source_file": "C:\\sgi-corban\\sgi-backend\\app\\api\\v1\\comercial\\contactos.py", "source_location": "L25", "weight": 1.0}, {"source": "comercial_contactos_rationale_36", "target": "comercial_contactos_create_contacto", "relation": "rationale_for", "confidence": "EXTRACTED", "source_file": "C:\\sgi-corban\\sgi-backend\\app\\api\\v1\\comercial\\contactos.py", "source_location": "L36", "weight": 1.0}, {"source": "comercial_contactos_rationale_49", "target": "comercial_contactos_set_contacto_principal", "relation": "rationale_for", "confidence": "EXTRACTED", "source_file": "C:\\sgi-corban\\sgi-backend\\app\\api\\v1\\comercial\\contactos.py", "source_location": "L49", "weight": 1.0}, {"source": "comercial_contactos_rationale_61", "target": "comercial_contactos_update_contacto", "relation": "rationale_for", "confidence": "EXTRACTED", "source_file": "C:\\sgi-corban\\sgi-backend\\app\\api\\v1\\comercial\\contactos.py", "source_location": "L61", "weight": 1.0}, {"source": "comercial_contactos_rationale_72", "target": "comercial_contactos_delete_contacto", "relation": "rationale_for", "confidence": "EXTRACTED", "source_file": "C:\\sgi-corban\\sgi-backend\\app\\api\\v1\\comercial\\contactos.py", "source_location": "L72", "weight": 1.0}, {"source": "comercial_contactos_rationale_86", "target": "comercial_contactos_get_contactos_paginados", "relation": "rationale_for", "confidence": "EXTRACTED", "source_file": "C:\\sgi-corban\\sgi-backend\\app\\api\\v1\\comercial\\contactos.py", "source_location": "L86", "weight": 1.0}, {"source": "comercial_contactos_rationale_96", "target": "comercial_contactos_get_estadisticas", "relation": "rationale_for", "confidence": "EXTRACTED", "source_file": "C:\\sgi-corban\\sgi-backend\\app\\api\\v1\\comercial\\contactos.py", "source_location": "L96", "weight": 1.0}, {"source": "comercial_contactos_rationale_108", "target": "comercial_contactos_get_kpis_gestion", "relation": "rationale_for", "confidence": "EXTRACTED", "source_file": "C:\\sgi-corban\\sgi-backend\\app\\api\\v1\\comercial\\contactos.py", "source_location": "L108", "weight": 1.0}, {"source": "comercial_contactos_rationale_118", "target": "comercial_contactos_assign_leads_batch", "relation": "rationale_for", "confidence": "EXTRACTED", "source_file": "C:\\sgi-corban\\sgi-backend\\app\\api\\v1\\comercial\\contactos.py", "source_location": "L118", "weight": 1.0}, {"source": "comercial_contactos_rationale_132", "target": "comercial_contactos_get_mis_contactos_asignados", "relation": "rationale_for", "confidence": "EXTRACTED", "source_file": "C:\\sgi-corban\\sgi-backend\\app\\api\\v1\\comercial\\contactos.py", "source_location": "L132", "weight": 1.0}, {"source": "comercial_contactos_rationale_144", "target": "comercial_contactos_cargar_base", "relation": "rationale_for", "confidence": "EXTRACTED", "source_file": "C:\\sgi-corban\\sgi-backend\\app\\api\\v1\\comercial\\contactos.py", "source_location": "L144", "weight": 1.0}, {"source": "comercial_contactos_rationale_155", "target": "comercial_contactos_create_contacto_manual", "relation": "rationale_for", "confidence": "EXTRACTED", "source_file": "C:\\sgi-corban\\sgi-backend\\app\\api\\v1\\comercial\\contactos.py", "source_location": "L155", "weight": 1.0}, {"source": "comercial_contactos_rationale_167", "target": "comercial_contactos_asignar_lead_manualmente", "relation": "rationale_for", "confidence": "EXTRACTED", "source_file": "C:\\sgi-corban\\sgi-backend\\app\\api\\v1\\comercial\\contactos.py", "source_location": "L167", "weight": 1.0}, {"source": "comercial_contactos_rationale_180", "target": "comercial_contactos_actualizar_feedback", "relation": "rationale_for", "confidence": "EXTRACTED", "source_file": "C:\\sgi-corban\\sgi-backend\\app\\api\\v1\\comercial\\contactos.py", "source_location": "L180", "weight": 1.0}, {"source": "comercial_contactos_rationale_190", "target": "comercial_contactos_enviar_feedback_lote", "relation": "rationale_for", "confidence": "EXTRACTED", "source_file": "C:\\sgi-corban\\sgi-backend\\app\\api\\v1\\comercial\\contactos.py", "source_location": "L190", "weight": 1.0}, {"source": "comercial_contactos_rationale_200", "target": "comercial_contactos_get_filtros_base", "relation": "rationale_for", "confidence": "EXTRACTED", "source_file": "C:\\sgi-corban\\sgi-backend\\app\\api\\v1\\comercial\\contactos.py", "source_location": "L200", "weight": 1.0}], "raw_calls": [{"caller_nid": "comercial_contactos_get_contactos", "callee": "ContactosService", "is_member_call": false, "source_file": "C:\\sgi-corban\\sgi-backend\\app\\api\\v1\\comercial\\contactos.py", "source_location": "L26"}, {"caller_nid": "comercial_contactos_get_contactos", "callee": "get_contactos_by_ruc", "is_member_call": true, "source_file": "C:\\sgi-corban\\sgi-backend\\app\\api\\v1\\comercial\\contactos.py", "source_location": "L27"}, {"caller_nid": "comercial_contactos_create_contacto", "callee": "ContactosService", "is_member_call": false, "source_file": "C:\\sgi-corban\\sgi-backend\\app\\api\\v1\\comercial\\contactos.py", "source_location": "L37"}, {"caller_nid": "comercial_contactos_set_contacto_principal", "callee": "ContactosService", "is_member_call": false, "source_file": "C:\\sgi-corban\\sgi-backend\\app\\api\\v1\\comercial\\contactos.py", "source_location": "L50"}, {"caller_nid": "comercial_contactos_update_contacto", "callee": "ContactosService", "is_member_call": false, "source_file": "C:\\sgi-corban\\sgi-backend\\app\\api\\v1\\comercial\\contactos.py", "source_location": "L62"}, {"caller_nid": "comercial_contactos_delete_contacto", "callee": "ContactosService", "is_member_call": false, "source_file": "C:\\sgi-corban\\sgi-backend\\app\\api\\v1\\comercial\\contactos.py", "source_location": "L73"}, {"caller_nid": "comercial_contactos_get_contactos_paginados", "callee": "ContactosService", "is_member_call": false, "source_file": "C:\\sgi-corban\\sgi-backend\\app\\api\\v1\\comercial\\contactos.py", "source_location": "L87"}, {"caller_nid": "comercial_contactos_get_contactos_paginados", "callee": "get_contactos_paginado", "is_member_call": true, "source_file": "C:\\sgi-corban\\sgi-backend\\app\\api\\v1\\comercial\\contactos.py", "source_location": "L88"}, {"caller_nid": "comercial_contactos_get_estadisticas", "callee": "ContactosService", "is_member_call": false, "source_file": "C:\\sgi-corban\\sgi-backend\\app\\api\\v1\\comercial\\contactos.py", "source_location": "L97"}, {"caller_nid": "comercial_contactos_get_kpis_gestion", "callee": "ContactosService", "is_member_call": false, "source_file": "C:\\sgi-corban\\sgi-backend\\app\\api\\v1\\comercial\\contactos.py", "source_location": "L109"}, {"caller_nid": "comercial_contactos_assign_leads_batch", "callee": "ContactosService", "is_member_call": false, "source_file": "C:\\sgi-corban\\sgi-backend\\app\\api\\v1\\comercial\\contactos.py", "source_location": "L119"}, {"caller_nid": "comercial_contactos_get_mis_contactos_asignados", "callee": "ContactosService", "is_member_call": false, "source_file": "C:\\sgi-corban\\sgi-backend\\app\\api\\v1\\comercial\\contactos.py", "source_location": "L133"}, {"caller_nid": "comercial_contactos_cargar_base", "callee": "ContactosService", "is_member_call": false, "source_file": "C:\\sgi-corban\\sgi-backend\\app\\api\\v1\\comercial\\contactos.py", "source_location": "L145"}, {"caller_nid": "comercial_contactos_create_contacto_manual", "callee": "ContactosService", "is_member_call": false, "source_file": "C:\\sgi-corban\\sgi-backend\\app\\api\\v1\\comercial\\contactos.py", "source_location": "L156"}, {"caller_nid": "comercial_contactos_asignar_lead_manualmente", "callee": "ContactosService", "is_member_call": false, "source_file": "C:\\sgi-corban\\sgi-backend\\app\\api\\v1\\comercial\\contactos.py", "source_location": "L168"}, {"caller_nid": "comercial_contactos_actualizar_feedback", "callee": "ContactosService", "is_member_call": false, "source_file": "C:\\sgi-corban\\sgi-backend\\app\\api\\v1\\comercial\\contactos.py", "source_location": "L181"}, {"caller_nid": "comercial_contactos_enviar_feedback_lote", "callee": "ContactosService", "is_member_call": false, "source_file": "C:\\sgi-corban\\sgi-backend\\app\\api\\v1\\comercial\\contactos.py", "source_location": "L191"}, {"caller_nid": "comercial_contactos_get_filtros_base", "callee": "ContactosService", "is_member_call": false, "source_file": "C:\\sgi-corban\\sgi-backend\\app\\api\\v1\\comercial\\contactos.py", "source_location": "L201"}]}