{"nodes": [{"id": "c_sgi_corban_sgi_backend_scripts_limpiar_instancia_py", "label": "limpiar_instancia.py", "file_type": "code", "source_file": "C:\\sgi-corban\\sgi-backend\\scripts\\limpiar_instancia.py", "source_location": "L1"}, {"id": "scripts_limpiar_instancia_limpiar", "label": "limpiar()", "file_type": "code", "source_file": "C:\\sgi-corban\\sgi-backend\\scripts\\limpiar_instancia.py", "source_location": "L11"}], "edges": [{"source": "c_sgi_corban_sgi_backend_scripts_limpiar_instancia_py", "target": "asyncio", "relation": "imports", "context": "import", "confidence": "EXTRACTED", "source_file": "C:\\sgi-corban\\sgi-backend\\scripts\\limpiar_instancia.py", "source_location": "L1", "weight": 1.0}, {"source": "c_sgi_corban_sgi_backend_scripts_limpiar_instancia_py", "target": "sys", "relation": "imports", "context": "import", "confidence": "EXTRACTED", "source_file": "C:\\sgi-corban\\sgi-backend\\scripts\\limpiar_instancia.py", "source_location": "L2", "weight": 1.0}, {"source": "c_sgi_corban_sgi_backend_scripts_limpiar_instancia_py", "target": "os", "relation": "imports", "context": "import", "confidence": "EXTRACTED", "source_file": "C:\\sgi-corban\\sgi-backend\\scripts\\limpiar_instancia.py", "source_location": "L3", "weight": 1.0}, {"source": "c_sgi_corban_sgi_backend_scripts_limpiar_instancia_py", "target": "sqlalchemy", "relation": "imports_from", "context": "import", "confidence": "EXTRACTED", "source_file": "C:\\sgi-corban\\sgi-backend\\scripts\\limpiar_instancia.py", "source_location": "L7", "weight": 1.0}, {"source": "c_sgi_corban_sgi_backend_scripts_limpiar_instancia_py", "target": "app_database_db_connection", "relation": "imports_from", "context": "import", "confidence": "EXTRACTED", "source_file": "C:\\sgi-corban\\sgi-backend\\scripts\\limpiar_instancia.py", "source_location": "L8", "weight": 1.0}, {"source": "c_sgi_corban_sgi_backend_scripts_limpiar_instancia_py", "target": "scripts_limpiar_instancia_limpiar", "relation": "contains", "confidence": "EXTRACTED", "source_file": "C:\\sgi-corban\\sgi-backend\\scripts\\limpiar_instancia.py", "source_location": "L11", "weight": 1.0}], "raw_calls": [{"caller_nid": "scripts_limpiar_instancia_limpiar", "callee": "begin", "is_member_call": true, "source_file": "C:\\sgi-corban\\sgi-backend\\scripts\\limpiar_instancia.py", "source_location": "L12"}, {"caller_nid": "scripts_limpiar_instancia_limpiar", "callee": "execute", "is_member_call": true, "source_file": "C:\\sgi-corban\\sgi-backend\\scripts\\limpiar_instancia.py", "source_location": "L13"}, {"caller_nid": "scripts_limpiar_instancia_limpiar", "callee": "text", "is_member_call": false, "source_file": "C:\\sgi-corban\\sgi-backend\\scripts\\limpiar_instancia.py", "source_location": "L14"}]}